archaea/__init__.py
archaea/earcut/README.md
archaea/earcut/__init__.py
archaea/earcut/earcut.py
archaea/earcut/earcut3d.py
archaea/geometry/__init__.py
archaea/geometry/bounding_box.py
archaea/geometry/coordinate_array.py
archaea/geometry/face.py
archaea/geometry/line_segment.py
archaea/geometry/loop.py
archaea/geometry/mesh.py
archaea/geometry/orientation.py
archaea/geometry/plane.py
archaea/geometry/point2d.py
archaea/geometry/point3d.py
archaea/geometry/polyline.py
archaea/geometry/utils.py
archaea/geometry/vector.py
archaea/geometry/vector2d.py
archaea/geometry/vector3d.py
archaea/writer/__init__.py
archaea/writer/test.stl
archaea/writer/to_manual_stl.py
archaea/writer/to_stl.py
archaea-1.1.28.dist-info/LICENSE
archaea-1.1.28.dist-info/LICENSE.txt
archaea-1.1.28.dist-info/METADATA
archaea-1.1.28.dist-info/WHEEL
archaea-1.1.28.dist-info/RECORD
