Metadata-Version: 2.1
Name: archaea
Version: 1.1.28
Summary: Playground for geometry.
Home-page: https://github.com/archaeans/archaea
License: Apache-2.0
Keywords: geometry,mesh,stl,triangulation
Author: Oğuzhan Koral
Author-email: oguzhankoral@gmail.com
Requires-Python: >=3.10,<4.0
Classifier: Development Status :: 3 - Alpha
Classifier: Intended Audience :: Developers
Classifier: Intended Audience :: Science/Research
Classifier: License :: OSI Approved :: Apache Software License
Classifier: Programming Language :: Python :: 3
Classifier: Programming Language :: Python :: 3.10
Classifier: Programming Language :: Python :: 3.11
Classifier: Topic :: Multimedia :: Graphics :: 3D Modeling
Classifier: Topic :: Scientific/Engineering :: Mathematics
Requires-Dist: numpy (>=1.24.2,<2.0.0)
Requires-Dist: numpy-stl (>=3.0.0,<4.0.0)
Project-URL: Repository, https://github.com/archaeans/archaea
